AcdhArcheAssets/__init__.py
AcdhArcheAssets/file_formats.py
AcdhArcheAssets/formats.json
AcdhArcheAssets/uriNormRules.json
AcdhArcheAssets/uri_norm_rules.py
acdh_arche_assets-3.25.0.dist-info/licenses/LICENSE
tests/__init__.py
tests/test_file_formats.py
tests/test_normalizer.py
acdh_arche_assets-3.25.0.dist-info/METADATA
acdh_arche_assets-3.25.0.dist-info/WHEEL
acdh_arche_assets-3.25.0.dist-info/top_level.txt
acdh_arche_assets-3.25.0.dist-info/RECORD
