Metadata-Version: 2.4
Name: acdh_arche-assets
Version: 3.25.0
Summary: A set of static assets used (mainly) for ARCHE data preprocessing
Home-page: https://github.com/acdh-oeaw/arche-assets
Author: Mateusz Żółtak
Author-email: mzoltak@oeaw.ac.at
Classifier: Programming Language :: Python :: 3
Classifier: License :: OSI Approved :: MIT License
Classifier: Operating System :: OS Independent
License-File: LICENSE
Requires-Dist: importlib-resources<7,>=6.4.5
Dynamic: author
Dynamic: author-email
Dynamic: classifier
Dynamic: description
Dynamic: description-content-type
Dynamic: home-page
Dynamic: license-file
Dynamic: requires-dist
Dynamic: summary
